ifes_apt_tc_data_modeling/__init__.py
ifes_apt_tc_data_modeling/_version.py
ifes_apt_tc_data_modeling/mkdocs.py
ifes_apt_tc_data_modeling/analysisset/README.md
ifes_apt_tc_data_modeling/analysisset/__init__.py
ifes_apt_tc_data_modeling/analysisset/analysisset_reader.py
ifes_apt_tc_data_modeling/apt/README.md
ifes_apt_tc_data_modeling/apt/__init__.py
ifes_apt_tc_data_modeling/apt/apt6_headers.py
ifes_apt_tc_data_modeling/apt/apt6_reader.py
ifes_apt_tc_data_modeling/apt/apt6_sections.py
ifes_apt_tc_data_modeling/apt/apt6_sections_branches.py
ifes_apt_tc_data_modeling/apt/apt6_utils.py
ifes_apt_tc_data_modeling/ato/README.md
ifes_apt_tc_data_modeling/ato/__init__.py
ifes_apt_tc_data_modeling/ato/ato_reader.py
ifes_apt_tc_data_modeling/ato/matlab/ato.m
ifes_apt_tc_data_modeling/cameca/README.md
ifes_apt_tc_data_modeling/cameca/__init__.py
ifes_apt_tc_data_modeling/cameca/cameca_reader.py
ifes_apt_tc_data_modeling/cameca/cameca_utils.py
ifes_apt_tc_data_modeling/csv/README.md
ifes_apt_tc_data_modeling/csv/__init__.py
ifes_apt_tc_data_modeling/csv/csv_reader.py
ifes_apt_tc_data_modeling/env/README.md
ifes_apt_tc_data_modeling/env/__init__.py
ifes_apt_tc_data_modeling/env/env_reader.py
ifes_apt_tc_data_modeling/epos/README.md
ifes_apt_tc_data_modeling/epos/__init__.py
ifes_apt_tc_data_modeling/epos/epos_reader.py
ifes_apt_tc_data_modeling/fig/README.md
ifes_apt_tc_data_modeling/fig/__init__.py
ifes_apt_tc_data_modeling/fig/fig_reader.py
ifes_apt_tc_data_modeling/fig/matlab/matlab_fig_to_txt.m
ifes_apt_tc_data_modeling/imago/README.md
ifes_apt_tc_data_modeling/imago/__init__.py
ifes_apt_tc_data_modeling/imago/imago_reader.py
ifes_apt_tc_data_modeling/ops/README.md
ifes_apt_tc_data_modeling/ops/__init__.py
ifes_apt_tc_data_modeling/ops/ops_reader.py
ifes_apt_tc_data_modeling/pos/README.md
ifes_apt_tc_data_modeling/pos/__init__.py
ifes_apt_tc_data_modeling/pos/pos_reader.py
ifes_apt_tc_data_modeling/pyccapt/README.md
ifes_apt_tc_data_modeling/pyccapt/__init__.py
ifes_apt_tc_data_modeling-0.4.0.dist-info/licenses/LICENSE
ifes_apt_tc_data_modeling-0.4.0.dist-info/METADATA
ifes_apt_tc_data_modeling-0.4.0.dist-info/WHEEL
ifes_apt_tc_data_modeling-0.4.0.dist-info/top_level.txt
ifes_apt_tc_data_modeling-0.4.0.dist-info/RECORD
