Metadata-Version: 2.4
Name: ifes_apt_tc_data_modeling
Version: 0.4.0
Summary: Working with file formats and data models in atom probe tomography and related field-ion microscopy (atom probe microscopy).
Author: The NOMAD Authors
License: 
Project-URL: Homepage, https://github.com/atomprobe-tc/ifes_apt_tc_data_modeling
Classifier: Programming Language :: Python :: 3.10
Classifier: Programming Language :: Python :: 3.11
Classifier: Programming Language :: Python :: 3.12
Classifier: Programming Language :: Python :: 3.13
Classifier: License :: OSI Approved :: Apache Software License
Classifier: Operating System :: OS Independent
Requires-Python: >=3.10
License-File: LICENSE
Requires-Dist: h5py>=3.6.0
Requires-Dist: radioactivedecay>=0.4.16
Requires-Dist: ase>=3.19.0
Requires-Dist: pandas>=2
Requires-Dist: pint
Requires-Dist: numpy
Requires-Dist: tables
Requires-Dist: flatdict
Requires-Dist: xmltodict
Provides-Extra: dev
Requires-Dist: mypy; extra == "dev"
Requires-Dist: ruff>=0.14.0; extra == "dev"
Requires-Dist: types-xmltodict; extra == "dev"
Requires-Dist: types-pyyaml; extra == "dev"
Requires-Dist: pandas-stubs; extra == "dev"
Requires-Dist: pytest; extra == "dev"
Requires-Dist: pre-commit; extra == "dev"
Provides-Extra: docs
Requires-Dist: mkdocs; extra == "docs"
Requires-Dist: mkdocs-material; extra == "docs"
Requires-Dist: mkdocs-material-extensions; extra == "docs"
Requires-Dist: mkdocs-macros-plugin; extra == "docs"
Requires-Dist: pymdown-extensions; extra == "docs"
Requires-Dist: mkdocs-click; extra == "docs"
Provides-Extra: ipynb
Requires-Dist: jupyter; extra == "ipynb"
Requires-Dist: jupyterlab; extra == "ipynb"
Requires-Dist: jupyterlab_h5web; extra == "ipynb"
Dynamic: license-file
